pypro4sail/__init__.py
pypro4sail/cma.py
pypro4sail/cost_functions.py
pypro4sail/four_sail.py
pypro4sail/four_sail_jacobian.py
pypro4sail/machine_learning_regression.py
pypro4sail/prospect.py
pypro4sail/prospect_d_spectra.txt
pypro4sail/prospect_jacobian.py
pypro4sail/pypro4sail.py
pypro4sail/radiation_helpers.py
pypro4sail/spectral_library.py
pypro4sail/spectra/sensor_response_functions/Landsat5.txt
pypro4sail/spectra/sensor_response_functions/Landsat7.txt
pypro4sail/spectra/sensor_response_functions/Landsat8.txt
pypro4sail/spectra/sensor_response_functions/Landsat9.txt
pypro4sail/spectra/sensor_response_functions/PRISMA.txt
pypro4sail/spectra/sensor_response_functions/Sentinel2A.txt
pypro4sail/spectra/sensor_response_functions/Sentinel2B.txt
pypro4sail/spectra/sensor_response_functions/Sentinel2C.txt
pypro4sail/spectra/sensor_response_functions/Sentinel3A_SYN.txt
pypro4sail/spectra/sensor_response_functions/Sentinel3B_SYN.txt
pypro4sail/spectra/sensor_response_functions/micasense.txt
pypro4sail/spectra/soil_spectral_library/ProSAIL_DrySoil.txt
pypro4sail/spectra/soil_spectral_library/ProSAIL_WetSoil.txt
pypro4sail/spectra/soil_spectral_library/ipgp.jussieu.soil.prosail.dry.coarse.1.spectrum.txt
pypro4sail/spectra/soil_spectral_library/ipgp.jussieu.soil.prosail.wet.coarse.2.spectrum.txt
pypro4sail/spectra/soil_spectral_library/jhu.becknic.soil.alfisol.fragiboralf.coarse.86P1994.spectrum.txt
pypro4sail/spectra/soil_spectral_library/jhu.becknic.soil.alfisol.haploxeralf.coarse.87P313.spectrum.txt
pypro4sail/spectra/soil_spectral_library/jhu.becknic.soil.alfisol.haplustalf.coarse.87P3468.spectrum.txt
pypro4sail/spectra/soil_spectral_library/jhu.becknic.soil.alfisol.haplustalf.coarse.87P3665.spectrum.txt
pypro4sail/spectra/soil_spectral_library/jhu.becknic.soil.alfisol.haplustalf.coarse.87P3671.spectrum.txt
pypro4sail/spectra/soil_spectral_library/jhu.becknic.soil.alfisol.paleustalf.coarse.87P1087.spectrum.txt
radiative_transfer_models-1.6.2.dist-info/licenses/LICENSE
radiative_transfer_models-1.6.2.dist-info/METADATA
radiative_transfer_models-1.6.2.dist-info/WHEEL
radiative_transfer_models-1.6.2.dist-info/top_level.txt
radiative_transfer_models-1.6.2.dist-info/RECORD
