Metadata-Version: 2.4
Name: radiative-transfer-models
Version: 1.6.2
Summary: Vectorized vesions of the ProspectD and 4SAIL Radiative Transfer Models for simulating the transmission of radiation in leaves and canopies
Author-email: Héctor Nieto <hector.nieto@csic.es>
License-Expression: GPL-3.0-or-later
Project-URL: Homepage, https://github.com/hectornieto/pypro4sail
Project-URL: Documentation, https://pypro4sail.readthedocs.io
Keywords: Prospect,4SAIL,Radiative Transfer Model,RTM,Remote Sensing
Classifier: Development Status :: 5 - Production/Stable
Classifier: Intended Audience :: Science/Research
Classifier: Topic :: Scientific/Engineering
Classifier: Topic :: Software Development :: Libraries :: Python Modules
Classifier: Programming Language :: Python
Classifier: Programming Language :: Python :: 3
Requires-Python: >=3.6
License-File: LICENSE
Requires-Dist: numpy
Requires-Dist: scipy
Requires-Dist: pandas
Requires-Dist: matplotlib
Requires-Dist: scikit-learn
Requires-Dist: joblib
Requires-Dist: salib
Requires-Dist: Py6S
Provides-Extra: intelex
Requires-Dist: scikit-learn-intelex; extra == "intelex"
Dynamic: license-file
